rtsp_to_webrtc/__init__.py
rtsp_to_webrtc/client.py
rtsp_to_webrtc/diagnostics.py
rtsp_to_webrtc/exceptions.py
rtsp_to_webrtc/interface.py
rtsp_to_webrtc/py.typed
rtsp_to_webrtc/web_client.py
rtsp_to_webrtc/webrtc_client.py
rtsp_to_webrtc-0.6.1.dist-info/LICENSE
rtsp_to_webrtc-0.6.1.dist-info/METADATA
rtsp_to_webrtc-0.6.1.dist-info/WHEEL
rtsp_to_webrtc-0.6.1.dist-info/top_level.txt
rtsp_to_webrtc-0.6.1.dist-info/RECORD
